{
  "hash": "de1be94d",
  "browserHash": "e8196d48",
  "optimized": {
    "react": {
      "src": "../../node_modules/react/index.js",
      "file": "react.js",
      "fileHash": "9fad78ce",
      "needsInterop": true
    },
    "react-dom/client": {
      "src": "../../node_modules/react-dom/client.js",
      "file": "react-dom_client.js",
      "fileHash": "e9635295",
      "needsInterop": true
    },
    "react-router-dom": {
      "src": "../../node_modules/react-router-dom/dist/index.js",
      "file": "react-router-dom.js",
      "fileHash": "34575f1c",
      "needsInterop": false
    },
    "@material-tailwind/react": {
      "src": "../../node_modules/@material-tailwind/react/index.js",
      "file": "@material-tailwind_react.js",
      "fileHash": "87f03e5c",
      "needsInterop": true
    }
  },
  "chunks": {
    "chunk-W35RGOJH": {
      "file": "chunk-W35RGOJH.js"
    },
    "chunk-2FATVHAI": {
      "file": "chunk-2FATVHAI.js"
    }
  }
}